Lab 7/PIPO/pipo.v
module pipo4(clk, rst, pi, po);
    input clk, rst;
    input [3:0] pi;
    output [3:0] po;
    reg [3:0] q;
    assign po = q;
    always @(posedge clk or posedge rst)
    if (rst) q <= 4'b0000;
    else q <= pi;
endmodule

`timescale 1ps/1ps
module tb_pipo4;
reg clk, rst;
reg [3:0] pi;
wire [3:0] po;
pipo4 dut(clk, rst, pi, po);
initial begin
$monitor("clk=%b rst=%b pi=%b po=%b",clk,rst,pi,po);
$dumpfile("pipo.vcd");
$dumpvars(0, tb_pipo4);
clk = 0; rst = 1; pi = 4'b0000;
#10 rst = 0;
pi = 4'b1010; #10;
pi = 4'b1100; #10;
pi = 4'b1111; #10;
pi = 4'b0001; #10;
#20 $finish;
end
always #5 clk = ~clk;
endmodule

Lab 7/PIPO/pipo.vcd
$date
	Mon Oct 27 20:23:00 2025
$end
$version
	Icarus Verilog
$end
$timescale
	1ps
$end
$scope module tb_pipo4 $end
$var wire 4 ! po [3:0] $end
$var reg 1 " clk $end
$var reg 4 # pi [3:0] $end
$var reg 1 $ rst $end
$scope module dut $end
$var wire 1 " clk $end
$var wire 4 % pi [3:0] $end
$var wire 4 & po [3:0] $end
$var wire 1 $ rst $end
$var reg 4 ' q [3:0] $end
$upscope $end
$upscope $end
$enddefinitions $end
$comment Show the parameter values. $end
$dumpall
$end
#0
$dumpvars
b0 '
b0 &
b0 %
1$
b0 #
0"
b0 !
$end
#5
1"
#10
0"
b1010 #
b1010 %
0$
#15
b1010 !
b1010 &
b1010 '
1"
#20
0"
b1100 #
b1100 %
#25
b1100 !
b1100 &
b1100 '
1"
#30
0"
b1111 #
b1111 %
#35
b1111 !
b1111 &
b1111 '
1"
#40
0"
b1 #
b1 %
#45
b1 !
b1 &
b1 '
1"
