Lab 8/Down Counter/down_counter.v
module jk_ff(
    input wire clk,
    input wire reset,
    input wire J,
    input wire K,
    output reg Q
);
    always @(posedge clk or posedge reset) begin
        if (reset)
            Q <= 1'b1;       // Start at 1 for proper down-counter MSB init
        else begin
            case ({J, K})
                2'b00: Q <= Q;
                2'b01: Q <= 1'b0;
                2'b10: Q <= 1'b1;
                2'b11: Q <= ~Q;
            endcase
        end
    end
endmodule


module down_counter_jk(
    input wire clk,
    input wire reset,
    output wire [3:0] Q
);
    wire t1 = ~Q[0];
    wire t2 = (~Q[1]) & (~Q[0]);
    wire t3 = (~Q[2]) & (~Q[1]) & (~Q[0]);

    jk_ff ff0(clk, reset, 1'b1, 1'b1, Q[0]);
    jk_ff ff1(clk, reset, t1,   t1,   Q[1]);
    jk_ff ff2(clk, reset, t2,   t2,   Q[2]);
    jk_ff ff3(clk, reset, t3,   t3,   Q[3]);
endmodule


module tb_down_counter_jk;
    reg clk;
    reg reset;
    wire [3:0] Q;

    down_counter_jk uut (
        .clk(clk),
        .reset(reset),
        .Q(Q)
    );

    always #5 clk = ~clk;

    initial begin
        $dumpfile("waves.vcd");
        $dumpvars(0, tb_down_counter_jk);

        $monitor("Time=%0t | clk=%b | reset=%b | Q=%b",$time, clk, reset, Q);

        clk = 0;
        reset = 1;
        #15 reset = 0;

        #200;
        $stop;
    end
endmodule

Lab 8/Down Counter/waves.vcd
$date
	Mon Nov 10 10:05:49 2025
$end
$version
	Icarus Verilog
$end
$timescale
	1s
$end
$scope module tb_down_counter_jk $end
$var wire 4 ! Q [3:0] $end
$var reg 1 " clk $end
$var reg 1 # reset $end
$scope module uut $end
$var wire 1 " clk $end
$var wire 1 # reset $end
$var wire 1 $ t1 $end
$var wire 1 % t2 $end
$var wire 1 & t3 $end
$var wire 4 ' Q [3:0] $end
$scope module ff0 $end
$var wire 1 ( J $end
$var wire 1 ) K $end
$var wire 1 " clk $end
$var wire 1 # reset $end
$var reg 1 * Q $end
$upscope $end
$scope module ff1 $end
$var wire 1 $ J $end
$var wire 1 $ K $end
$var wire 1 " clk $end
$var wire 1 # reset $end
$var reg 1 + Q $end
$upscope $end
$scope module ff2 $end
$var wire 1 % J $end
$var wire 1 % K $end
$var wire 1 " clk $end
$var wire 1 # reset $end
$var reg 1 , Q $end
$upscope $end
$scope module ff3 $end
$var wire 1 & J $end
$var wire 1 & K $end
$var wire 1 " clk $end
$var wire 1 # reset $end
$var reg 1 - Q $end
$upscope $end
$upscope $end
$upscope $end
$enddefinitions $end
$comment Show the parameter values. $end
$dumpall
$end
#0
$dumpvars
1-
1,
1+
1*
1)
1(
b1111 '
0&
0%
0$
1#
0"
b1111 !
$end
#5
1"
#10
0"
#15
1$
b1110 !
b1110 '
0*
1"
0#
#20
0"
#25
0$
0+
b1101 !
b1101 '
1*
1"
#30
0"
#35
1%
1$
b1100 !
b1100 '
0*
1"
#40
0"
#45
0%
0$
0,
1+
b1011 !
b1011 '
1*
1"
#50
0"
#55
1$
b1010 !
b1010 '
0*
1"
#60
0"
#65
0$
0+
b1001 !
b1001 '
1*
1"
#70
0"
#75
1&
1%
1$
b1000 !
b1000 '
0*
1"
#80
0"
#85
0&
0%
0$
0-
1,
1+
b111 !
b111 '
1*
1"
#90
0"
#95
1$
b110 !
b110 '
0*
1"
#100
0"
#105
0$
0+
b101 !
b101 '
1*
1"
#110
0"
#115
1%
1$
b100 !
b100 '
0*
1"
#120
0"
#125
0%
0$
0,
1+
b11 !
b11 '
1*
1"
#130
0"
#135
1$
b10 !
b10 '
0*
1"
#140
0"
#145
0$
0+
b1 !
b1 '
1*
1"
#150
0"
#155
1&
1%
1$
b0 !
b0 '
0*
1"
#160
0"
#165
0&
0%
0$
1-
1,
1+
b1111 !
b1111 '
1*
1"
#170
0"
#175
1$
b1110 !
b1110 '
0*
1"
#180
0"
#185
0$
0+
b1101 !
b1101 '
1*
1"
#190
0"
#195
1%
1$
b1100 !
b1100 '
0*
1"
#200
0"
#205
0%
0$
0,
1+
b1011 !
b1011 '
1*
1"
