Lab 8/Down Counter/down_counter.v
module down_counter (
    input  wire clk,        // Clock
    input  wire reset,      // Asynchronous active-high reset
    output reg  [3:0] count // 4-bit counter output
);

    always @(posedge clk or posedge reset) begin
        if (reset)
            count <= 4'b1111;      // Start from max (15)
        else
            count <= count - 1'b1; // Decrement
    end
endmodule

`timescale 1ps/1ps

module tb_down_counter;

    reg clk;
    reg reset;
    wire [3:0] count;

    // Instantiate DUT
    down_counter uut (
        .clk(clk),
        .reset(reset),
        .count(count)
    );

    // Clock generation: 10-unit period
    always #5 clk = ~clk;

    initial begin
        $dumpfile("waves.vcd");
        $dumpvars(0, tb_down_counter);

        $monitor("Time = %0t | clk = %b | reset = %b | count = %b",$time, clk, reset, count);
        clk = 0;
        reset = 1;       // Apply reset (count = 15)
        #15 reset = 0;   // Release reset
        #200;            // Let it run
        $stop;
    end

endmodule

Lab 8/Down Counter/waves.vcd
$date
	Mon Nov 10 00:55:54 2025
$end
$version
	Icarus Verilog
$end
$timescale
	1ps
$end
$scope module tb_down_counter $end
$var wire 4 ! count [3:0] $end
$var reg 1 " clk $end
$var reg 1 # reset $end
$scope module uut $end
$var wire 1 " clk $end
$var wire 1 # reset $end
$var reg 4 $ count [3:0] $end
$upscope $end
$upscope $end
$enddefinitions $end
$comment Show the parameter values. $end
$dumpall
$end
#0
$dumpvars
b1111 $
1#
0"
b1111 !
$end
#5
1"
#10
0"
#15
b1110 !
b1110 $
1"
0#
#20
0"
#25
b1101 !
b1101 $
1"
#30
0"
#35
b1100 !
b1100 $
1"
#40
0"
#45
b1011 !
b1011 $
1"
#50
0"
#55
b1010 !
b1010 $
1"
#60
0"
#65
b1001 !
b1001 $
1"
#70
0"
#75
b1000 !
b1000 $
1"
#80
0"
#85
b111 !
b111 $
1"
#90
0"
#95
b110 !
b110 $
1"
#100
0"
#105
b101 !
b101 $
1"
#110
0"
#115
b100 !
b100 $
1"
#120
0"
#125
b11 !
b11 $
1"
#130
0"
#135
b10 !
b10 $
1"
#140
0"
#145
b1 !
b1 $
1"
#150
0"
#155
b0 !
b0 $
1"
#160
0"
#165
b1111 !
b1111 $
1"
#170
0"
#175
b1110 !
b1110 $
1"
#180
0"
#185
b1101 !
b1101 $
1"
#190
0"
#195
b1100 !
b1100 $
1"
#200
0"
#205
b1011 !
b1011 $
1"
