Lab 6/JK Flip Flop/jk_flip_flop.v
module jk_ff (
    input J, K, clk, rst,
    output reg Q,
    output Qbar
);
    assign Qbar=~Q;
    always @(posedge clk or posedge rst) begin
        if (rst)
            Q <= 0;
        else begin
            case ({J, K})
                2'b00: Q <= Q;       
                2'b01: Q <= 0;       
                2'b10: Q <= 1;       
                2'b11: Q <= ~Q;
            endcase
        end
    end
endmodule
`timescale 1ps/1ps
module tb_jk_ff;
    reg J, K, clk, rst;
    wire Q,Qbar;
    jk_ff uut (
        .J(J),
        .K(K),
        .clk(clk),
        .rst(rst),
        .Q(Q),
        .Qbar(Qbar)
    );
    always #5 clk = ~clk;
    initial begin
        clk = 0;
        rst = 1;
        J = 0; K = 0;
        #10 rst = 0;
        #10 J = 0; K = 0;   
        #10 J = 0; K = 1;   
        #10 J = 1; K = 0;   
        #10 J = 1; K = 1;   
        #10 J = 1; K = 1;   
        #10 J = 0; K = 0;   
        $finish;
    end
    initial begin
        $monitor("Clk=%b | J=%b K=%b | Q=%b Qbar=%b", clk, J, K, Q, Qbar);
    end
    initial begin
        $dumpfile("jk_ff.vcd");
        $dumpvars(0,tb_jk_ff);
    end
endmodule

Lab 6/JK Flip Flop/jk_ff.vcd
$date
	Mon Oct 13 11:00:31 2025
$end
$version
	Icarus Verilog
$end
$timescale
	1ps
$end
$scope module tb_jk_ff $end
$var wire 1 ! Qbar $end
$var wire 1 " Q $end
$var reg 1 # J $end
$var reg 1 $ K $end
$var reg 1 % clk $end
$var reg 1 & rst $end
$scope module uut $end
$var wire 1 # J $end
$var wire 1 $ K $end
$var wire 1 ! Qbar $end
$var wire 1 % clk $end
$var wire 1 & rst $end
$var reg 1 " Q $end
$upscope $end
$upscope $end
$enddefinitions $end
$comment Show the parameter values. $end
$dumpall
$end
#0
$dumpvars
1&
0%
0$
0#
0"
1!
$end
#5
1%
#10
0%
0&
#15
1%
#20
0%
#25
1%
#30
0%
1$
#35
1%
#40
0%
0$
1#
#45
0!
1"
1%
#50
0%
1$
#55
1!
0"
1%
#60
0%
#65
0!
1"
1%
#70
0%
0$
0#
