Lab 4/Demultiplexer/demultiplexer.v
module demux8to1 (
    input  din,          
    input  [2:0] sel,    
    output reg [7:0] y   
);
    always @(*) begin
        y = 8'b0;               // Default all outputs off
        if (din) begin
            case (sel)
                3'b000: y[0] = 1;
                3'b001: y[1] = 1;
                3'b010: y[2] = 1;
                3'b011: y[3] = 1;
                3'b100: y[4] = 1;
                3'b101: y[5] = 1;
                3'b110: y[6] = 1;
                3'b111: y[7] = 1;
            endcase
        end
    end
endmodule

`timescale 1ps/1ps
module tb_demux8to1;
    reg din;             
    reg [2:0] sel;       
    wire [7:0] y;        
    demux8to1 uut (
        .din(din),
        .sel(sel),
        .y(y)
    );
    integer i;
    initial begin
        $display("Sel\tDin\tY");
        $monitor("%b\t%b\t%b", sel, din, y);

        // Loop through all select lines
        for (i = 0; i < 8; i = i + 1) begin
            sel = i;
            din = 1;
            #5;
        end

        #10 $finish;
    end
    initial begin
        $dumpfile("demux.vcd");
        $dumpvars(0,tb_demux8to1);
    end
endmodule

Lab 4/Demultiplexer/demux.vcd
$date
	Mon Sep 22 10:26:22 2025
$end
$version
	Icarus Verilog
$end
$timescale
	1ps
$end
$scope module tb_demux8to1 $end
$var wire 8 ! y [7:0] $end
$var reg 1 " din $end
$var reg 3 # sel [2:0] $end
$var integer 32 $ i [31:0] $end
$scope module uut $end
$var wire 1 " din $end
$var wire 3 % sel [2:0] $end
$var reg 8 & y [7:0] $end
$upscope $end
$upscope $end
$enddefinitions $end
$comment Show the parameter values. $end
$dumpall
$end
#0
$dumpvars
b1 &
b0 %
b0 $
b0 #
1"
b1 !
$end
#5
b10 !
b10 &
b1 #
b1 %
b1 $
#10
b100 !
b100 &
b10 #
b10 %
b10 $
#15
b1000 !
b1000 &
b11 #
b11 %
b11 $
#20
b10000 !
b10000 &
b100 #
b100 %
b100 $
#25
b100000 !
b100000 &
b101 #
b101 %
b101 $
#30
b1000000 !
b1000000 &
b110 #
b110 %
b110 $
#35
b10000000 !
b10000000 &
b111 #
b111 %
b111 $
#40
b1000 $
