Lab 7/PISO/piso.v
module piso4(clk, rst, load, pi, so);
    input clk, rst, load;
    input [3:0] pi;
    output so;
    reg [3:0] q;
    assign so = q[3];
    always @(posedge clk or posedge rst)
    if (rst) q <= 4'b0000;
    else if (load) q <= pi;
    else q <= {q[2:0], 1'b0};
endmodule

`timescale 1ps/1ps
module tb_piso4;
reg clk, rst, load;
reg [3:0] pi;
wire so;
piso4 dut(clk, rst, load, pi, so);
initial begin
$monitor("clk=%b rst=%b load=%b pi=%b so=%b",clk,rst,load,pi,so);
$dumpfile("piso.vcd");
$dumpvars(0, tb_piso4);
clk = 0; rst = 1; load = 0; pi = 4'b0000;
#10 rst = 0;
pi = 4'b1011; load = 1; #10;
load = 0; #40;
#20 $finish;
end
always #5 clk = ~clk;
endmodule

Lab 7/PISO/piso.vcd
$date
	Mon Oct 27 20:20:04 2025
$end
$version
	Icarus Verilog
$end
$timescale
	1ps
$end
$scope module tb_piso4 $end
$var wire 1 ! so $end
$var reg 1 " clk $end
$var reg 1 # load $end
$var reg 4 $ pi [3:0] $end
$var reg 1 % rst $end
$scope module dut $end
$var wire 1 " clk $end
$var wire 1 # load $end
$var wire 4 & pi [3:0] $end
$var wire 1 % rst $end
$var wire 1 ! so $end
$var reg 4 ' q [3:0] $end
$upscope $end
$upscope $end
$enddefinitions $end
$comment Show the parameter values. $end
$dumpall
$end
#0
$dumpvars
b0 '
b0 &
1%
b0 $
0#
0"
0!
$end
#5
1"
#10
0"
1#
b1011 $
b1011 &
0%
#15
1!
b1011 '
1"
#20
0"
0#
#25
0!
b110 '
1"
#30
0"
#35
1!
b1100 '
1"
#40
0"
#45
b1000 '
1"
#50
0"
#55
0!
b0 '
1"
