Lab 5/D flip flop/d_flip_flop.v
module d_flip_flop (
    input wire d,       
    input wire clk,      
    input wire rst_n,    
    output reg q         
);
    always @(posedge clk or negedge rst_n) begin
        if (!rst_n)
            q <= 1'b0; 
        else
            q <= d;    
    end
endmodule
`timescale 1ps/1ps
module tb_d_flip_flop;
    reg d;
    reg clk;
    reg rst_n;
    wire q;
    d_flip_flop uut (
        .d(d),
        .clk(clk),
        .rst_n(rst_n),
        .q(q)
    );
    initial begin
        clk = 0;
        forever #5 clk = ~clk; 
    end
    initial begin
        rst_n = 0; d = 0; #10; 
        rst_n = 1; #10; 
        d = 1; #10; 
        d = 0; #10; 
        d = 1; #10; 
        rst_n = 0; #10; 
        rst_n = 1; #10; 
        d = 0; #10; 
        d = 1; #20; 
        $finish; 
    end
    initial begin
        $monitor("rst_n: %b | d: %b | q: %b",rst_n, d, q);
    end
    initial begin
        $dumpfile("tb_d_flip_flop.vcd");
        $dumpvars(0, tb_d_flip_flop);
    end
endmodule

Lab 5/D flip flop/tb_d_flip_flop.vcd
$date
	Mon Oct 06 10:59:45 2025
$end
$version
	Icarus Verilog
$end
$timescale
	1ps
$end
$scope module tb_d_flip_flop $end
$var wire 1 ! q $end
$var reg 1 " clk $end
$var reg 1 # d $end
$var reg 1 $ rst_n $end
$scope module uut $end
$var wire 1 " clk $end
$var wire 1 # d $end
$var wire 1 $ rst_n $end
$var reg 1 ! q $end
$upscope $end
$upscope $end
$enddefinitions $end
$comment Show the parameter values. $end
$dumpall
$end
#0
$dumpvars
0$
0#
0"
0!
$end
#5
1"
#10
0"
1$
#15
1"
#20
0"
1#
#25
1!
1"
#30
0"
0#
#35
0!
1"
#40
0"
1#
#45
1!
1"
#50
0!
0"
0$
#55
1"
#60
0"
1$
#65
1!
1"
#70
0"
0#
#75
0!
1"
#80
0"
1#
#85
1!
1"
