Lab 4/Multiplexer/multiplexer.v
module mux8to1 (
    input  [7:0] d,
    input  [2:0] sel,
    output reg y          
);
    always @(*) begin
        case (sel)
            3'b000: y = d[0];
            3'b001: y = d[1];
            3'b010: y = d[2];
            3'b011: y = d[3];
            3'b100: y = d[4];
            3'b101: y = d[5];
            3'b110: y = d[6];
            3'b111: y = d[7];
            default: y = 1'b0;
        endcase
    end
endmodule

`timescale 1ps/1ps
module tb_mux8to1;
    reg  [7:0] d;     
    reg  [2:0] sel;    
    wire y;            
    mux8to1 uut (
        .d(d),
        .sel(sel),
        .y(y)
    );

    integer i;
    initial begin
        $display("Sel\tD\t\tY");
        $monitor("%b\t%b\t%b", sel, d, y);

        // Test 16 cases: each input bit once with 0, once with 1
        for (i = 0; i < 8; i = i + 1) begin
            sel = i;              // Select input i
            
            // Case 1: input bit = 0
            d = 8'b0;             // all 0s
            #5;

            // Case 2: input bit = 1
            d = (1 << i);         // only d[i] = 1
            #5;
        end

        #10 $finish;
    end
    initial begin
        $dumpfile("mux.vcd");
        $dumpvars(0,tb_mux8to1);
    end
endmodule

Lab 4/Multiplexer/mux.vcd
$date
	Mon Sep 22 10:24:25 2025
$end
$version
	Icarus Verilog
$end
$timescale
	1ps
$end
$scope module tb_mux8to1 $end
$var wire 1 ! y $end
$var reg 8 " d [7:0] $end
$var reg 3 # sel [2:0] $end
$var integer 32 $ i [31:0] $end
$scope module uut $end
$var wire 8 % d [7:0] $end
$var wire 3 & sel [2:0] $end
$var reg 1 ! y $end
$upscope $end
$upscope $end
$enddefinitions $end
$comment Show the parameter values. $end
$dumpall
$end
#0
$dumpvars
b0 &
b0 %
b0 $
b0 #
b0 "
0!
$end
#5
1!
b1 "
b1 %
#10
0!
b0 "
b0 %
b1 #
b1 &
b1 $
#15
1!
b10 "
b10 %
#20
0!
b0 "
b0 %
b10 #
b10 &
b10 $
#25
1!
b100 "
b100 %
#30
0!
b0 "
b0 %
b11 #
b11 &
b11 $
#35
1!
b1000 "
b1000 %
#40
0!
b0 "
b0 %
b100 #
b100 &
b100 $
#45
1!
b10000 "
b10000 %
#50
0!
b0 "
b0 %
b101 #
b101 &
b101 $
#55
1!
b100000 "
b100000 %
#60
0!
b0 "
b0 %
b110 #
b110 &
b110 $
#65
1!
b1000000 "
b1000000 %
#70
0!
b0 "
b0 %
b111 #
b111 &
b111 $
#75
1!
b10000000 "
b10000000 %
#80
b1000 $
