Lab 8/Ring Counter/ring_counter.v
module jk_ff(
    input wire clk,
    input wire reset,
    input wire J,
    input wire K,
    output reg Q,
    input wire init       
);
    always @(posedge clk or posedge reset) begin
        if (reset)
            Q <= init;        
        else begin
            case ({J, K})
                2'b00: Q <= Q;
                2'b01: Q <= 1'b0;
                2'b10: Q <= 1'b1;
                2'b11: Q <= ~Q;
            endcase
        end
    end
endmodule


module ring_counter_jk(
    input wire clk,
    input wire reset,
    output wire [3:0] Q
);
    wire [3:0] D = {Q[2], Q[1], Q[0], Q[3]};

    wire J0 = ~Q[0] & D[0];
    wire K0 =  Q[0] & ~D[0];

    wire J1 = ~Q[1] & D[1];
    wire K1 =  Q[1] & ~D[1];

    wire J2 = ~Q[2] & D[2];
    wire K2 =  Q[2] & ~D[2];

    wire J3 = ~Q[3] & D[3];
    wire K3 =  Q[3] & ~D[3];

    // Initial state = 1000 (Q3 = 1)
    jk_ff ff0(clk, reset, J0, K0, Q[0], 1'b0);
    jk_ff ff1(clk, reset, J1, K1, Q[1], 1'b0);
    jk_ff ff2(clk, reset, J2, K2, Q[2], 1'b0);
    jk_ff ff3(clk, reset, J3, K3, Q[3], 1'b1);
endmodule


module tb_ring_counter_jk;
    reg clk;
    reg reset;
    wire [3:0] Q;

    ring_counter_jk uut (
        .clk(clk),
        .reset(reset),
        .Q(Q)
    );

    always #5 clk = ~clk;

    initial begin
        $dumpfile("waves.vcd");
        $dumpvars(0, tb_ring_counter_jk);

        $monitor("Time=%0t | clk=%b | reset=%b | Q=%b",$time, clk, reset, Q);
        clk = 0;
        reset = 1;
        #15 reset = 0;
        #200;
        $stop;
    end
endmodule

Lab 8/Ring Counter/waves.vcd
$date
	Mon Nov 10 10:20:33 2025
$end
$version
	Icarus Verilog
$end
$timescale
	1s
$end
$scope module tb_ring_counter_jk $end
$var wire 4 ! Q [3:0] $end
$var reg 1 " clk $end
$var reg 1 # reset $end
$scope module uut $end
$var wire 1 $ J0 $end
$var wire 1 % J1 $end
$var wire 1 & J2 $end
$var wire 1 ' J3 $end
$var wire 1 ( K0 $end
$var wire 1 ) K1 $end
$var wire 1 * K2 $end
$var wire 1 + K3 $end
$var wire 1 " clk $end
$var wire 1 # reset $end
$var wire 4 , Q [3:0] $end
$var wire 4 - D [3:0] $end
$scope module ff0 $end
$var wire 1 $ J $end
$var wire 1 ( K $end
$var wire 1 " clk $end
$var wire 1 . init $end
$var wire 1 # reset $end
$var reg 1 / Q $end
$upscope $end
$scope module ff1 $end
$var wire 1 % J $end
$var wire 1 ) K $end
$var wire 1 " clk $end
$var wire 1 0 init $end
$var wire 1 # reset $end
$var reg 1 1 Q $end
$upscope $end
$scope module ff2 $end
$var wire 1 & J $end
$var wire 1 * K $end
$var wire 1 " clk $end
$var wire 1 2 init $end
$var wire 1 # reset $end
$var reg 1 3 Q $end
$upscope $end
$scope module ff3 $end
$var wire 1 ' J $end
$var wire 1 + K $end
$var wire 1 " clk $end
$var wire 1 4 init $end
$var wire 1 # reset $end
$var reg 1 5 Q $end
$upscope $end
$upscope $end
$upscope $end
$enddefinitions $end
$comment Show the parameter values. $end
$dumpall
$end
#0
$dumpvars
15
14
03
02
01
00
0/
0.
b1 -
b1000 ,
1+
0*
0)
0(
0'
0&
0%
1$
1#
0"
b1000 !
$end
#5
1"
#10
0"
#15
1(
1%
0$
0+
b10 -
1/
b1 !
b1 ,
05
1"
0#
#20
0"
#25
1)
1&
0%
0(
b100 -
11
b10 !
b10 ,
0/
1"
#30
0"
#35
1*
0&
1'
0)
b1000 -
01
b100 !
b100 ,
13
1"
#40
0"
#45
1+
1$
0'
0*
b1 -
15
b1000 !
b1000 ,
03
1"
#50
0"
#55
1(
1%
0$
0+
b10 -
1/
b1 !
b1 ,
05
1"
#60
0"
#65
1)
1&
0%
0(
b100 -
11
b10 !
b10 ,
0/
1"
#70
0"
#75
1*
0&
1'
0)
b1000 -
01
b100 !
b100 ,
13
1"
#80
0"
#85
1+
1$
0'
0*
b1 -
15
b1000 !
b1000 ,
03
1"
#90
0"
#95
1(
1%
0$
0+
b10 -
1/
b1 !
b1 ,
05
1"
#100
0"
#105
1)
1&
0%
0(
b100 -
11
b10 !
b10 ,
0/
1"
#110
0"
#115
1*
0&
1'
0)
b1000 -
01
b100 !
b100 ,
13
1"
#120
0"
#125
1+
1$
0'
0*
b1 -
15
b1000 !
b1000 ,
03
1"
#130
0"
#135
1(
1%
0$
0+
b10 -
1/
b1 !
b1 ,
05
1"
#140
0"
#145
1)
1&
0%
0(
b100 -
11
b10 !
b10 ,
0/
1"
#150
0"
#155
1*
0&
1'
0)
b1000 -
01
b100 !
b100 ,
13
1"
#160
0"
#165
1+
1$
0'
0*
b1 -
15
b1000 !
b1000 ,
03
1"
#170
0"
#175
1(
1%
0$
0+
b10 -
1/
b1 !
b1 ,
05
1"
#180
0"
#185
1)
1&
0%
0(
b100 -
11
b10 !
b10 ,
0/
1"
#190
0"
#195
1*
0&
1'
0)
b1000 -
01
b100 !
b100 ,
13
1"
#200
0"
#205
1+
1$
0'
0*
b1 -
15
b1000 !
b1000 ,
03
1"
